[{"start": 81696359, "end": 81938479, "inSample1": 1, "inSample2": 0}, {"start": 81722766, "end": 81722770, "inSample1": 1, "inSample2": 1}, {"start": 81739095, "end": 81923238, "inSample1": 1, "inSample2": 1}, {"start": 81739101, "end": 81897716, "inSample1": 0, "inSample2": 1}, {"start": 81916836, "end": 4472061934, "inSample1": 1, "inSample2": 1}, {"start": 81739095, "end": 81901703, "inSample1": 1, "inSample2": 1}, {"start": 81669734, "end": 81674480, "inSample1": 1, "inSample2": 1}, {"start": 81916832, "end": 81916836, "inSample1": 0, "inSample2": 0}, {"start": 81696364, "end": 81824243, "inSample1": 1, "inSample2": 1}, {"start": 81897725, "end": 81916824, "inSample1": 1, "inSample2": 1}, {"start": 81722758, "end": 81923238, "inSample1": 1, "inSample2": 1}, {"start": 81739105, "end": 81901711, "inSample1": 1, "inSample2": 1}, {"start": 81722766, "end": 81938479, "inSample1": 1, "inSample2": 1}, {"start": 81901703, "end": 82002051, "inSample1": 1, "inSample2": 1}, {"start": 81923243, "end": 81923248, "inSample1": 0, "inSample2": 0}, {"start": 81674472, "end": 81881540, "inSample1": 1, "inSample2": 0}, {"start": 81897716, "end": 81901707, "inSample1": 1, "inSample2": 1}, {"start": 81674472, "end": 81722761, "inSample1": 1, "inSample2": 1}, {"start": 81897714, "end": 81923243, "inSample1": 1, "inSample2": 1}, {"start": 81685989, "end": 81938481, "inSample1": 0, "inSample2": 0}, {"start": 81901713, "end": 82002058, "inSample1": 1, "inSample2": 1}, {"start": 81674472, "end": 81674480, "inSample1": 0, "inSample2": 0}, {"start": 81901711, "end": 81901713, "inSample1": 0, "inSample2": 1}, {"start": 81916832, "end": 82002056, "inSample1": 1, "inSample2": 1}, {"start": 81938479, "end": 82072689, "inSample1": 1, "inSample2": 1}, {"start": 81685989, "end": 81938483, "inSample1": 0, "inSample2": 1}, {"start": 81916828, "end": 82001700, "inSample1": 1, "inSample2": 1}, {"start": 81897725, "end": 81916828, "inSample1": 1, "inSample2": 0}, {"start": 81938481, "end": 81938483, "inSample1": 1, "inSample2": 1}, {"start": 81897714, "end": 81923238, "inSample1": 0, "inSample2": 1}, {"start": 81739103, "end": 81923243, "inSample1": 0, "inSample2": 1}, {"start": 81916824, "end": 4472061947, "inSample1": 1, "inSample2": 1}, {"start": 81669723, "end": 81674472, "inSample1": 1, "inSample2": 1}, {"start": 81739103, "end": 81901707, "inSample1": 1, "inSample2": 1}, {"start": 81722766, "end": 81923248, "inSample1": 1, "inSample2": 1}, {"start": 81696359, "end": 81696361, "inSample1": 0, "inSample2": 1}, {"start": 81696359, "end": 81722762, "inSample1": 1, "inSample2": 1}, {"start": 81739103, "end": 81739105, "inSample1": 1, "inSample2": 1}, {"start": 81897719, "end": 82001700, "inSample1": 1, "inSample2": 1}, {"start": 81916836, "end": 82002058, "inSample1": 1, "inSample2": 1}, {"start": 81739105, "end": 81923248, "inSample1": 1, "inSample2": 0}, {"start": 81722762, "end": 81923243, "inSample1": 1, "inSample2": 1}, {"start": 81901707, "end": 82001700, "inSample1": 0, "inSample2": 0}, {"start": 81897719, "end": 81897725, "inSample1": 0, "inSample2": 1}, {"start": 81901711, "end": 82002056, "inSample1": 1, "inSample2": 1}, {"start": 81739105, "end": 81739108, "inSample1": 1, "inSample2": 0}, {"start": 81897719, "end": 82002051, "inSample1": 1, "inSample2": 1}, {"start": 82001700, "end": 82002056, "inSample1": 1, "inSample2": 1}, {"start": 81685989, "end": 81722770, "inSample1": 1, "inSample2": 1}, {"start": 81824243, "end": 82072689, "inSample1": 1, "inSample2": 1}, {"start": 81916828, "end": 81916832, "inSample1": 1, "inSample2": 1}, {"start": 81685989, "end": 81685990, "inSample1": 1, "inSample2": 1}, {"start": 81669723, "end": 81696359, "inSample1": 1, "inSample2": 1}, {"start": 81722758, "end": 81722761, "inSample1": 1, "inSample2": 1}, {"start": 81669723, "end": 81669734, "inSample1": 1, "inSample2": 1}, {"start": 81722762, "end": 81722766, "inSample1": 1, "inSample2": 1}, {"start": 81739095, "end": 81739101, "inSample1": 1, "inSample2": 1}, {"start": 81897716, "end": 81897719, "inSample1": 1, "inSample2": 0}, {"start": 81669734, "end": 81696361, "inSample1": 1, "inSample2": 1}, {"start": 81897716, "end": 81901703, "inSample1": 1, "inSample2": 1}, {"start": 81739108, "end": 81923249, "inSample1": 1, "inSample2": 0}, {"start": 81696361, "end": 81696364, "inSample1": 1, "inSample2": 1}, {"start": 81938479, "end": 81938481, "inSample1": 1, "inSample2": 1}, {"start": 81923248, "end": 81923249, "inSample1": 0, "inSample2": 0}, {"start": 81722761, "end": 81722762, "inSample1": 1, "inSample2": 1}, {"start": 81901707, "end": 81901711, "inSample1": 1, "inSample2": 1}, {"start": 81739108, "end": 81901713, "inSample1": 1, "inSample2": 1}, {"start": 81722770, "end": 81923249, "inSample1": 1, "inSample2": 1}, {"start": 81722761, "end": 81897714, "inSample1": 1, "inSample2": 1}, {"start": 81739101, "end": 81897714, "inSample1": 0, "inSample2": 0}, {"start": 81722758, "end": 81938473, "inSample1": 1, "inSample2": 1}, {"start": 81881540, "end": 81938473, "inSample1": 1, "inSample2": 1}, {"start": 81739101, "end": 81739103, "inSample1": 0, "inSample2": 0}, {"start": 82002056, "end": 82002058, "inSample1": 1, "inSample2": 1}, {"start": 81916824, "end": 82002051, "inSample1": 1, "inSample2": 1}]