[{"start": 264503085, "end": 3627944967, "inSample1": 1, "inSample2": 1}, {"start": 249237646, "end": 276698442, "inSample1": 1, "inSample2": 1}, {"start": 264503074, "end": 264503075, "inSample1": 1, "inSample2": 1}, {"start": 264503075, "end": 264504559, "inSample1": 0, "inSample2": 0}, {"start": 317405522, "end": 317405554, "inSample1": 1, "inSample2": 1}, {"start": 276695117, "end": 292698768, "inSample1": 1, "inSample2": 1}, {"start": 276695112, "end": 276695117, "inSample1": 0, "inSample2": 1}, {"start": 31002119, "end": 264503507, "inSample1": 1, "inSample2": 1}, {"start": 264503075, "end": 264503078, "inSample1": 0, "inSample2": 1}, {"start": 264504171, "end": 264504176, "inSample1": 0, "inSample2": 1}, {"start": 244956312, "end": 264503916, "inSample1": 1, "inSample2": 1}, {"start": 30914761, "end": 266456553, "inSample1": 1, "inSample2": 1}, {"start": 31002119, "end": 264503917, "inSample1": 1, "inSample2": 1}, {"start": 264503078, "end": 264503085, "inSample1": 1, "inSample2": 0}, {"start": 31002121, "end": 264503917, "inSample1": 1, "inSample2": 1}, {"start": 264346775, "end": 317405554, "inSample1": 1, "inSample2": 1}, {"start": 31002121, "end": 293134689, "inSample1": 1, "inSample2": 1}, {"start": 276698441, "end": 276698442, "inSample1": 0, "inSample2": 0}, {"start": 31002112, "end": 31002114, "inSample1": 1, "inSample2": 1}, {"start": 244956423, "end": 264061616, "inSample1": 1, "inSample2": 1}, {"start": 31002114, "end": 264503078, "inSample1": 1, "inSample2": 1}, {"start": 264503323, "end": 264503325, "inSample1": 1, "inSample2": 1}, {"start": 244956302, "end": 244956315, "inSample1": 1, "inSample2": 1}, {"start": 276695109, "end": 276695112, "inSample1": 0, "inSample2": 1}, {"start": 264503917, "end": 264504176, "inSample1": 1, "inSample2": 0}, {"start": 30914761, "end": 244956315, "inSample1": 1, "inSample2": 0}, {"start": 249237498, "end": 276699901, "inSample1": 1, "inSample2": 1}, {"start": 292698768, "end": 293134689, "inSample1": 0, "inSample2": 0}, {"start": 317405519, "end": 317405605, "inSample1": 1, "inSample2": 1}, {"start": 264346775, "end": 264503507, "inSample1": 0, "inSample2": 1}, {"start": 31002121, "end": 264503916, "inSample1": 1, "inSample2": 1}, {"start": 264503916, "end": 264504176, "inSample1": 1, "inSample2": 1}, {"start": 256227204, "end": 292705436, "inSample1": 1, "inSample2": 1}, {"start": 31002112, "end": 264503085, "inSample1": 1, "inSample2": 1}, {"start": 30914762, "end": 30914763, "inSample1": 1, "inSample2": 1}, {"start": 256227204, "end": 292705499, "inSample1": 1, "inSample2": 1}, {"start": 249237496, "end": 249237498, "inSample1": 1, "inSample2": 1}, {"start": 31002119, "end": 276695109, "inSample1": 1, "inSample2": 1}, {"start": 264503325, "end": 264503503, "inSample1": 1, "inSample2": 1}, {"start": 276695112, "end": 276696638, "inSample1": 1, "inSample2": 1}, {"start": 264503917, "end": 264504424, "inSample1": 1, "inSample2": 0}, {"start": 276695117, "end": 276698441, "inSample1": 1, "inSample2": 1}, {"start": 292703748, "end": 293134130, "inSample1": 1, "inSample2": 1}, {"start": 264503504, "end": 264503551, "inSample1": 1, "inSample2": 1}, {"start": 244956302, "end": 244956305, "inSample1": 1, "inSample2": 1}, {"start": 266456132, "end": 266456133, "inSample1": 1, "inSample2": 1}, {"start": 317405554, "end": 317405605, "inSample1": 1, "inSample2": 1}, {"start": 249237496, "end": 276699854, "inSample1": 1, "inSample2": 1}, {"start": 264504822, "end": 266456075, "inSample1": 1, "inSample2": 1}, {"start": 256227201, "end": 293169041, "inSample1": 1, "inSample2": 1}, {"start": 264061616, "end": 266456133, "inSample1": 0, "inSample2": 0}, {"start": 249237643, "end": 276695916, "inSample1": 1, "inSample2": 1}, {"start": 293134075, "end": 293134689, "inSample1": 1, "inSample2": 1}, {"start": 276695925, "end": 276698442, "inSample1": 0, "inSample2": 0}, {"start": 276695925, "end": 276695931, "inSample1": 0, "inSample2": 0}, {"start": 317405519, "end": 317405522, "inSample1": 1, "inSample2": 1}, {"start": 249237496, "end": 276697020, "inSample1": 0, "inSample2": 0}, {"start": 31002119, "end": 264062965, "inSample1": 1, "inSample2": 1}, {"start": 264061616, "end": 266456132, "inSample1": 1, "inSample2": 1}, {"start": 264503916, "end": 264504171, "inSample1": 1, "inSample2": 0}, {"start": 244956315, "end": 244956318, "inSample1": 1, "inSample2": 1}, {"start": 292703909, "end": 292705136, "inSample1": 1, "inSample2": 1}, {"start": 249237643, "end": 276695925, "inSample1": 1, "inSample2": 1}, {"start": 276695109, "end": 276695931, "inSample1": 1, "inSample2": 1}, {"start": 31002121, "end": 256227204, "inSample1": 1, "inSample2": 1}, {"start": 264346775, "end": 276695931, "inSample1": 0, "inSample2": 0}, {"start": 31002112, "end": 244956305, "inSample1": 1, "inSample2": 1}, {"start": 264503503, "end": 264503550, "inSample1": 1, "inSample2": 1}, {"start": 249237643, "end": 249237646, "inSample1": 1, "inSample2": 1}, {"start": 276695931, "end": 317405522, "inSample1": 0, "inSample2": 0}, {"start": 30914761, "end": 264504822, "inSample1": 0, "inSample2": 0}, {"start": 264346775, "end": 317405492, "inSample1": 1, "inSample2": 1}, {"start": 30914761, "end": 264061649, "inSample1": 1, "inSample2": 1}, {"start": 264503074, "end": 264503504, "inSample1": 1, "inSample2": 1}, {"start": 264061649, "end": 266456132, "inSample1": 1, "inSample2": 1}, {"start": 276695916, "end": 276699854, "inSample1": 1, "inSample2": 1}, {"start": 30914761, "end": 244956318, "inSample1": 1, "inSample2": 0}, {"start": 249237646, "end": 276697020, "inSample1": 1, "inSample2": 1}, {"start": 264503503, "end": 264503504, "inSample1": 1, "inSample2": 1}, {"start": 256227204, "end": 266456075, "inSample1": 1, "inSample2": 1}, {"start": 264503074, "end": 264503507, "inSample1": 1, "inSample2": 1}, {"start": 276697020, "end": 1643928024, "inSample1": 0, "inSample2": 0}, {"start": 292705498, "end": 292705499, "inSample1": 1, "inSample2": 1}, {"start": 276696638, "end": 276698442, "inSample1": 1, "inSample2": 1}, {"start": 31002119, "end": 264346775, "inSample1": 1, "inSample2": 1}, {"start": 276695931, "end": 276696638, "inSample1": 1, "inSample2": 1}, {"start": 256227201, "end": 292705499, "inSample1": 0, "inSample2": 0}, {"start": 276698441, "end": 1643928024, "inSample1": 1, "inSample2": 1}, {"start": 264504821, "end": 264504822, "inSample1": 1, "inSample2": 1}, {"start": 30914761, "end": 244956312, "inSample1": 1, "inSample2": 1}, {"start": 30914763, "end": 266988028, "inSample1": 1, "inSample2": 1}, {"start": 264503916, "end": 266456075, "inSample1": 0, "inSample2": 0}, {"start": 264503075, "end": 264503325, "inSample1": 1, "inSample2": 1}, {"start": 276695117, "end": 293134783, "inSample1": 1, "inSample2": 1}, {"start": 244956423, "end": 256227201, "inSample1": 1, "inSample2": 0}, {"start": 292698768, "end": 292703748, "inSample1": 1, "inSample2": 1}, {"start": 31002114, "end": 264504424, "inSample1": 1, "inSample2": 1}, {"start": 31002121, "end": 276695117, "inSample1": 1, "inSample2": 1}, {"start": 292703909, "end": 1643928024, "inSample1": 1, "inSample2": 1}, {"start": 31002114, "end": 264504559, "inSample1": 1, "inSample2": 1}, {"start": 264062965, "end": 276695112, "inSample1": 0, "inSample2": 0}, {"start": 276699854, "end": 276699901, "inSample1": 1, "inSample2": 1}, {"start": 31002121, "end": 264062965, "inSample1": 0, "inSample2": 1}, {"start": 244956305, "end": 244956312, "inSample1": 0, "inSample2": 0}, {"start": 244956423, "end": 256227204, "inSample1": 0, "inSample2": 1}, {"start": 31002119, "end": 264504559, "inSample1": 1, "inSample2": 1}, {"start": 30914761, "end": 30914762, "inSample1": 1, "inSample2": 1}, {"start": 264504171, "end": 264504424, "inSample1": 1, "inSample2": 1}, {"start": 256227201, "end": 266456133, "inSample1": 1, "inSample2": 1}, {"start": 244956315, "end": 266988028, "inSample1": 1, "inSample2": 1}]