[{"start": 42814912, "end": 42879517, "inSample1": 1, "inSample2": 1}, {"start": 42475220, "end": 42495042, "inSample1": 1, "inSample2": 1}, {"start": 42879517, "end": 42920298, "inSample1": 1, "inSample2": 1}, {"start": 42837474, "end": 42838029, "inSample1": 1, "inSample2": 1}, {"start": 42822285, "end": 42822287, "inSample1": 1, "inSample2": 1}, {"start": 42790407, "end": 42822285, "inSample1": 1, "inSample2": 1}, {"start": 42845524, "end": 42879520, "inSample1": 1, "inSample2": 1}, {"start": 42822276, "end": 42879512, "inSample1": 1, "inSample2": 1}, {"start": 42843382, "end": 42919530, "inSample1": 0, "inSample2": 0}, {"start": 42814912, "end": 42879512, "inSample1": 1, "inSample2": 1}, {"start": 42494745, "end": 42920301, "inSample1": 1, "inSample2": 1}, {"start": 42499610, "end": 42499886, "inSample1": 1, "inSample2": 1}, {"start": 42472598, "end": 42527849, "inSample1": 1, "inSample2": 1}, {"start": 42475215, "end": 42475220, "inSample1": 1, "inSample2": 0}, {"start": 42822266, "end": 42822268, "inSample1": 1, "inSample2": 0}, {"start": 42870562, "end": 42870564, "inSample1": 1, "inSample2": 1}, {"start": 42822283, "end": 42822285, "inSample1": 1, "inSample2": 1}, {"start": 42822287, "end": 42917138, "inSample1": 1, "inSample2": 1}, {"start": 42495056, "end": 42919530, "inSample1": 1, "inSample2": 1}, {"start": 42478977, "end": 42837474, "inSample1": 1, "inSample2": 1}, {"start": 42814910, "end": 42920295, "inSample1": 1, "inSample2": 1}, {"start": 42843385, "end": 42845524, "inSample1": 1, "inSample2": 1}, {"start": 42827705, "end": 42899931, "inSample1": 1, "inSample2": 1}, {"start": 42478977, "end": 42499888, "inSample1": 1, "inSample2": 1}, {"start": 42475215, "end": 42495037, "inSample1": 1, "inSample2": 1}, {"start": 42472584, "end": 42472594, "inSample1": 1, "inSample2": 1}, {"start": 42919530, "end": 42920301, "inSample1": 0, "inSample2": 0}, {"start": 42495048, "end": 42495056, "inSample1": 0, "inSample2": 0}, {"start": 42472573, "end": 42472575, "inSample1": 1, "inSample2": 0}, {"start": 42879632, "end": 42923491, "inSample1": 1, "inSample2": 1}, {"start": 42827708, "end": 42917138, "inSample1": 1, "inSample2": 1}, {"start": 42472576, "end": 42472584, "inSample1": 1, "inSample2": 1}, {"start": 42478972, "end": 42478977, "inSample1": 1, "inSample2": 1}, {"start": 42843382, "end": 42879520, "inSample1": 1, "inSample2": 1}, {"start": 42472575, "end": 42472576, "inSample1": 1, "inSample2": 1}, {"start": 42827708, "end": 42827711, "inSample1": 0, "inSample2": 0}, {"start": 42475220, "end": 42475235, "inSample1": 1, "inSample2": 0}, {"start": 42466367, "end": 42472573, "inSample1": 1, "inSample2": 1}, {"start": 42478967, "end": 42499886, "inSample1": 1, "inSample2": 1}, {"start": 42837482, "end": 42845524, "inSample1": 0, "inSample2": 0}, {"start": 42827725, "end": 42837482, "inSample1": 0, "inSample2": 1}, {"start": 42827719, "end": 42827723, "inSample1": 1, "inSample2": 1}, {"start": 42478963, "end": 42499610, "inSample1": 1, "inSample2": 1}, {"start": 42478977, "end": 42494745, "inSample1": 1, "inSample2": 1}, {"start": 42879517, "end": 42879520, "inSample1": 1, "inSample2": 1}, {"start": 42472584, "end": 42495030, "inSample1": 1, "inSample2": 1}, {"start": 42475238, "end": 42495056, "inSample1": 1, "inSample2": 1}, {"start": 42814910, "end": 42920298, "inSample1": 1, "inSample2": 0}, {"start": 42827714, "end": 42827719, "inSample1": 1, "inSample2": 1}, {"start": 42488263, "end": 42495030, "inSample1": 1, "inSample2": 1}, {"start": 42837474, "end": 42920301, "inSample1": 0, "inSample2": 1}, {"start": 42499608, "end": 42528992, "inSample1": 1, "inSample2": 1}, {"start": 42495042, "end": 42499886, "inSample1": 1, "inSample2": 1}, {"start": 42495037, "end": 42499608, "inSample1": 1, "inSample2": 1}, {"start": 42822268, "end": 42870562, "inSample1": 1, "inSample2": 1}, {"start": 42472575, "end": 42520784, "inSample1": 1, "inSample2": 1}, {"start": 42495034, "end": 42495037, "inSample1": 1, "inSample2": 1}, {"start": 42499886, "end": 42499888, "inSample1": 1, "inSample2": 1}, {"start": 42837477, "end": 42838029, "inSample1": 1, "inSample2": 1}, {"start": 42827723, "end": 42827725, "inSample1": 1, "inSample2": 1}, {"start": 42827714, "end": 42846108, "inSample1": 0, "inSample2": 0}, {"start": 42494745, "end": 42495056, "inSample1": 1, "inSample2": 1}, {"start": 42475238, "end": 42822266, "inSample1": 1, "inSample2": 1}, {"start": 42495034, "end": 42528992, "inSample1": 0, "inSample2": 1}, {"start": 42495042, "end": 42495048, "inSample1": 0, "inSample2": 0}, {"start": 42478961, "end": 42478963, "inSample1": 0, "inSample2": 1}, {"start": 42475235, "end": 42495048, "inSample1": 1, "inSample2": 1}, {"start": 42488263, "end": 461220613, "inSample1": 1, "inSample2": 1}, {"start": 42472594, "end": 42528992, "inSample1": 1, "inSample2": 1}, {"start": 42472576, "end": 42485424, "inSample1": 1, "inSample2": 1}, {"start": 42822283, "end": 42827711, "inSample1": 1, "inSample2": 1}, {"start": 42475235, "end": 42475238, "inSample1": 1, "inSample2": 0}, {"start": 42837474, "end": 42837477, "inSample1": 0, "inSample2": 1}, {"start": 42527849, "end": 42528992, "inSample1": 1, "inSample2": 1}, {"start": 42475212, "end": 42475215, "inSample1": 0, "inSample2": 0}, {"start": 42478967, "end": 42478972, "inSample1": 1, "inSample2": 0}, {"start": 42472594, "end": 42472598, "inSample1": 1, "inSample2": 1}, {"start": 42919530, "end": 42920298, "inSample1": 0, "inSample2": 1}, {"start": 42814910, "end": 42814912, "inSample1": 0, "inSample2": 0}, {"start": 42827719, "end": 42845524, "inSample1": 0, "inSample2": 1}, {"start": 42472573, "end": 42475212, "inSample1": 0, "inSample2": 1}, {"start": 42822276, "end": 42822283, "inSample1": 1, "inSample2": 1}, {"start": 42822266, "end": 42920295, "inSample1": 0, "inSample2": 0}, {"start": 42478963, "end": 42478967, "inSample1": 1, "inSample2": 1}, {"start": 42822283, "end": 42827714, "inSample1": 1, "inSample2": 1}, {"start": 42475212, "end": 42495034, "inSample1": 1, "inSample2": 1}, {"start": 42499608, "end": 42499610, "inSample1": 1, "inSample2": 1}, {"start": 42879512, "end": 42920295, "inSample1": 1, "inSample2": 1}, {"start": 42870564, "end": 42879632, "inSample1": 1, "inSample2": 1}, {"start": 42478961, "end": 42527849, "inSample1": 1, "inSample2": 1}, {"start": 42827705, "end": 42827708, "inSample1": 1, "inSample2": 1}, {"start": 42466367, "end": 461220613, "inSample1": 1, "inSample2": 1}, {"start": 42837477, "end": 42837482, "inSample1": 1, "inSample2": 1}, {"start": 42822285, "end": 42846108, "inSample1": 1, "inSample2": 1}, {"start": 42827711, "end": 42870564, "inSample1": 0, "inSample2": 0}, {"start": 42822268, "end": 42822276, "inSample1": 1, "inSample2": 1}, {"start": 42843382, "end": 42843385, "inSample1": 0, "inSample2": 1}, {"start": 42827714, "end": 42879517, "inSample1": 1, "inSample2": 1}, {"start": 42495037, "end": 42495042, "inSample1": 0, "inSample2": 0}, {"start": 42472576, "end": 42478991, "inSample1": 1, "inSample2": 1}, {"start": 42827723, "end": 42837482, "inSample1": 1, "inSample2": 1}, {"start": 42495048, "end": 42499888, "inSample1": 1, "inSample2": 1}, {"start": 42837474, "end": 42843385, "inSample1": 1, "inSample2": 1}, {"start": 42870562, "end": 42923491, "inSample1": 1, "inSample2": 0}, {"start": 42472584, "end": 42495034, "inSample1": 1, "inSample2": 1}, {"start": 42478972, "end": 42499888, "inSample1": 1, "inSample2": 0}, {"start": 42827702, "end": 42827705, "inSample1": 1, "inSample2": 1}]