[{"start": 1198789196, "end": 2306405274, "inSample1": 1, "inSample2": 1}, {"start": 380541239, "end": 673480311, "inSample1": 1, "inSample2": 1}, {"start": 673480322, "end": 1933857938, "inSample1": 1, "inSample2": 1}, {"start": 1307800903, "end": 1307800907, "inSample1": 0, "inSample2": 1}, {"start": 1933857950, "end": 2010601084, "inSample1": 1, "inSample2": 1}, {"start": 1307800007, "end": 1307800204, "inSample1": 1, "inSample2": 1}, {"start": 1933857948, "end": 2010601084, "inSample1": 1, "inSample2": 1}, {"start": 420298913, "end": 1933857745, "inSample1": 1, "inSample2": 1}, {"start": 1934476638, "end": 1934476652, "inSample1": 1, "inSample2": 1}, {"start": 1933170031, "end": 1933170037, "inSample1": 0, "inSample2": 1}, {"start": 1933857959, "end": 2010601084, "inSample1": 1, "inSample2": 1}, {"start": 1307800034, "end": 1307800754, "inSample1": 1, "inSample2": 0}, {"start": 1933857849, "end": 1935376454, "inSample1": 1, "inSample2": 1}, {"start": 1198728691, "end": 1307800868, "inSample1": 1, "inSample2": 1}, {"start": 1307800214, "end": 1307800880, "inSample1": 1, "inSample2": 0}, {"start": 1933857943, "end": 1933857948, "inSample1": 1, "inSample2": 0}, {"start": 1198728691, "end": 1307800081, "inSample1": 1, "inSample2": 1}, {"start": 1198789223, "end": 1935376273, "inSample1": 1, "inSample2": 1}, {"start": 516376508, "end": 1933170037, "inSample1": 0, "inSample2": 0}, {"start": 1307800766, "end": 1934476621, "inSample1": 1, "inSample2": 1}, {"start": 1307800127, "end": 1307800260, "inSample1": 1, "inSample2": 1}, {"start": 1933857826, "end": 1934641369, "inSample1": 1, "inSample2": 1}, {"start": 1933857685, "end": 1934476661, "inSample1": 1, "inSample2": 0}, {"start": 1933857686, "end": 1934476656, "inSample1": 1, "inSample2": 1}, {"start": 1933857745, "end": 1933857787, "inSample1": 0, "inSample2": 0}, {"start": 1307799655, "end": 1307799811, "inSample1": 1, "inSample2": 1}, {"start": 1819504377, "end": 1934476627, "inSample1": 1, "inSample2": 1}, {"start": 1933857950, "end": 1933857965, "inSample1": 1, "inSample2": 1}, {"start": 1934476660, "end": 1934476663, "inSample1": 1, "inSample2": 1}, {"start": 1307799448, "end": 1307799597, "inSample1": 1, "inSample2": 1}, {"start": 1935376451, "end": 1935376452, "inSample1": 1, "inSample2": 1}, {"start": 1307800321, "end": 1307800715, "inSample1": 1, "inSample2": 1}, {"start": 1307799622, "end": 1307799898, "inSample1": 1, "inSample2": 1}, {"start": 1934476645, "end": 1934476646, "inSample1": 1, "inSample2": 1}, {"start": 772389799, "end": 1307800367, "inSample1": 1, "inSample2": 1}, {"start": 1307799811, "end": 1307800332, "inSample1": 1, "inSample2": 0}, {"start": 1933857749, "end": 1933857804, "inSample1": 1, "inSample2": 1}, {"start": 364378028, "end": 1933857675, "inSample1": 0, "inSample2": 1}, {"start": 1307799597, "end": 1821055723, "inSample1": 1, "inSample2": 1}, {"start": 1307800905, "end": 3090332718, "inSample1": 1, "inSample2": 1}, {"start": 1934476655, "end": 1934476661, "inSample1": 1, "inSample2": 1}, {"start": 1198789223, "end": 1198789224, "inSample1": 1, "inSample2": 0}, {"start": 673480326, "end": 1933857960, "inSample1": 1, "inSample2": 0}, {"start": 1933857913, "end": 1933857932, "inSample1": 0, "inSample2": 1}, {"start": 1307800130, "end": 1307800775, "inSample1": 1, "inSample2": 0}, {"start": 1307799495, "end": 1307800146, "inSample1": 1, "inSample2": 1}, {"start": 1933857941, "end": 1934476670, "inSample1": 1, "inSample2": 1}, {"start": 673480326, "end": 673480327, "inSample1": 1, "inSample2": 1}, {"start": 1307800715, "end": 1307800902, "inSample1": 1, "inSample2": 1}, {"start": 1933857675, "end": 1934476647, "inSample1": 1, "inSample2": 1}, {"start": 1934476621, "end": 1934476627, "inSample1": 1, "inSample2": 0}, {"start": 560002145, "end": 1933857790, "inSample1": 1, "inSample2": 1}, {"start": 1198711162, "end": 1307800081, "inSample1": 1, "inSample2": 1}, {"start": 1307800577, "end": 1307800880, "inSample1": 1, "inSample2": 1}, {"start": 1307800801, "end": 1819504377, "inSample1": 1, "inSample2": 1}, {"start": 1934476627, "end": 1934476638, "inSample1": 0, "inSample2": 0}, {"start": 1933857678, "end": 1933857692, "inSample1": 0, "inSample2": 1}, {"start": 289698121, "end": 1307800874, "inSample1": 1, "inSample2": 1}, {"start": 1307800279, "end": 1307800512, "inSample1": 1, "inSample2": 0}, {"start": 370090296, "end": 520105026, "inSample1": 1, "inSample2": 1}, {"start": 1307799652, "end": 1307800737, "inSample1": 1, "inSample2": 1}, {"start": 1307799868, "end": 1819504178, "inSample1": 1, "inSample2": 1}, {"start": 1933857688, "end": 1934918105, "inSample1": 0, "inSample2": 0}, {"start": 673480322, "end": 1933857912, "inSample1": 1, "inSample2": 1}, {"start": 1307800007, "end": 1819504377, "inSample1": 1, "inSample2": 1}, {"start": 673480327, "end": 2633386343, "inSample1": 1, "inSample2": 1}, {"start": 1933169986, "end": 1933169993, "inSample1": 1, "inSample2": 1}, {"start": 1307800250, "end": 1935376328, "inSample1": 1, "inSample2": 0}, {"start": 364378028, "end": 520227659, "inSample1": 0, "inSample2": 1}, {"start": 1307799953, "end": 1307800275, "inSample1": 1, "inSample2": 1}, {"start": 1933857675, "end": 1933857678, "inSample1": 1, "inSample2": 1}, {"start": 1198789223, "end": 1307799929, "inSample1": 1, "inSample2": 1}, {"start": 1307800504, "end": 1307800841, "inSample1": 1, "inSample2": 1}, {"start": 1307800883, "end": 1933857746, "inSample1": 1, "inSample2": 1}, {"start": 1934918084, "end": 1934918096, "inSample1": 1, "inSample2": 1}, {"start": 364378102, "end": 1307800472, "inSample1": 1, "inSample2": 1}, {"start": 1198711166, "end": 1933857748, "inSample1": 1, "inSample2": 1}, {"start": 380528314, "end": 1307799451, "inSample1": 1, "inSample2": 1}, {"start": 1198728686, "end": 1307800219, "inSample1": 1, "inSample2": 1}, {"start": 1307800127, "end": 1307800907, "inSample1": 1, "inSample2": 1}, {"start": 560002145, "end": 1933857701, "inSample1": 1, "inSample2": 1}, {"start": 1933857703, "end": 1933857758, "inSample1": 0, "inSample2": 1}, {"start": 1933857701, "end": 1935376450, "inSample1": 1, "inSample2": 0}, {"start": 1933857704, "end": 1935376328, "inSample1": 1, "inSample2": 1}, {"start": 1933011313, "end": 1933169993, "inSample1": 1, "inSample2": 1}, {"start": 1307799691, "end": 1307800472, "inSample1": 1, "inSample2": 1}, {"start": 1934476670, "end": 1934641371, "inSample1": 0, "inSample2": 1}, {"start": 380541239, "end": 1307800250, "inSample1": 0, "inSample2": 0}, {"start": 1307800202, "end": 1307800880, "inSample1": 1, "inSample2": 0}, {"start": 1307800577, "end": 1821055699, "inSample1": 1, "inSample2": 1}, {"start": 559386994, "end": 1307800113, "inSample1": 1, "inSample2": 1}, {"start": 380528315, "end": 1307800145, "inSample1": 1, "inSample2": 1}, {"start": 1307799433, "end": 1933857744, "inSample1": 0, "inSample2": 1}, {"start": 1307799495, "end": 1307800034, "inSample1": 1, "inSample2": 0}, {"start": 1307800610, "end": 1821055626, "inSample1": 1, "inSample2": 1}, {"start": 380528314, "end": 1307800279, "inSample1": 1, "inSample2": 1}, {"start": 1198728729, "end": 1933857775, "inSample1": 1, "inSample2": 1}, {"start": 520227659, "end": 1307799451, "inSample1": 0, "inSample2": 0}, {"start": 1307799652, "end": 1307800801, "inSample1": 1, "inSample2": 1}, {"start": 1933857745, "end": 1935376406, "inSample1": 1, "inSample2": 1}, {"start": 1933857965, "end": 2010601200, "inSample1": 0, "inSample2": 1}, {"start": 1933857815, "end": 1933857849, "inSample1": 1, "inSample2": 1}, {"start": 1198789199, "end": 1307799929, "inSample1": 1, "inSample2": 1}, {"start": 1933857939, "end": 2010601148, "inSample1": 1, "inSample2": 0}, {"start": 1933857899, "end": 2455770980, "inSample1": 0, "inSample2": 0}, {"start": 1307799868, "end": 1307800146, "inSample1": 1, "inSample2": 0}, {"start": 1307799982, "end": 1307800146, "inSample1": 1, "inSample2": 1}, {"start": 1934476627, "end": 1934476633, "inSample1": 1, "inSample2": 0}, {"start": 289697322, "end": 420298913, "inSample1": 1, "inSample2": 1}, {"start": 2010601053, "end": 2010601148, "inSample1": 1, "inSample2": 1}, {"start": 520227659, "end": 1307800504, "inSample1": 1, "inSample2": 0}, {"start": 1307800332, "end": 1307800717, "inSample1": 1, "inSample2": 1}, {"start": 1933170031, "end": 1933170039, "inSample1": 0, "inSample2": 0}, {"start": 1933857856, "end": 1934641369, "inSample1": 0, "inSample2": 1}, {"start": 1935376450, "end": 1935376454, "inSample1": 1, "inSample2": 1}, {"start": 1307800000, "end": 1933857835, "inSample1": 1, "inSample2": 1}, {"start": 2010601029, "end": 2010601084, "inSample1": 1, "inSample2": 1}, {"start": 559387050, "end": 1307800566, "inSample1": 1, "inSample2": 0}, {"start": 1307799868, "end": 1307800702, "inSample1": 1, "inSample2": 1}, {"start": 1307800250, "end": 1307800825, "inSample1": 1, "inSample2": 0}, {"start": 560002145, "end": 1933857699, "inSample1": 1, "inSample2": 1}, {"start": 673480325, "end": 1933857930, "inSample1": 1, "inSample2": 1}, {"start": 1307799566, "end": 1307800873, "inSample1": 1, "inSample2": 1}, {"start": 1933857921, "end": 2010601029, "inSample1": 1, "inSample2": 1}, {"start": 1933857952, "end": 1933857964, "inSample1": 1, "inSample2": 1}, {"start": 1933857699, "end": 1933857704, "inSample1": 0, "inSample2": 0}, {"start": 1933857749, "end": 1935376406, "inSample1": 1, "inSample2": 1}, {"start": 1307800260, "end": 1307800763, "inSample1": 0, "inSample2": 1}, {"start": 1307800202, "end": 1307800873, "inSample1": 0, "inSample2": 1}, {"start": 1307799637, "end": 1934476633, "inSample1": 1, "inSample2": 1}, {"start": 1307799637, "end": 1307800204, "inSample1": 1, "inSample2": 1}, {"start": 1307800081, "end": 1935376341, "inSample1": 1, "inSample2": 1}, {"start": 1307800845, "end": 1307800903, "inSample1": 1, "inSample2": 1}, {"start": 1933857840, "end": 1933857922, "inSample1": 1, "inSample2": 1}, {"start": 1307799566, "end": 1307799777, "inSample1": 1, "inSample2": 1}, {"start": 1933857849, "end": 1933857912, "inSample1": 1, "inSample2": 1}, {"start": 1933857825, "end": 1933857889, "inSample1": 1, "inSample2": 1}, {"start": 420298907, "end": 1933857720, "inSample1": 1, "inSample2": 1}, {"start": 420298913, "end": 1933857787, "inSample1": 1, "inSample2": 1}, {"start": 1307799495, "end": 1307799868, "inSample1": 0, "inSample2": 1}, {"start": 1307799828, "end": 1307800883, "inSample1": 1, "inSample2": 1}, {"start": 1307799622, "end": 1307800715, "inSample1": 1, "inSample2": 1}, {"start": 1307800841, "end": 1935376273, "inSample1": 1, "inSample2": 1}, {"start": 560002145, "end": 1935376451, "inSample1": 1, "inSample2": 1}, {"start": 380528315, "end": 1198789226, "inSample1": 1, "inSample2": 1}, {"start": 1933857798, "end": 1933857804, "inSample1": 1, "inSample2": 1}, {"start": 1933857794, "end": 1933857799, "inSample1": 1, "inSample2": 1}, {"start": 1933857825, "end": 1933857835, "inSample1": 1, "inSample2": 1}, {"start": 1307799929, "end": 1307800096, "inSample1": 1, "inSample2": 1}, {"start": 1307800219, "end": 1307800332, "inSample1": 1, "inSample2": 1}, {"start": 1198789187, "end": 2306405274, "inSample1": 1, "inSample2": 1}, {"start": 1933857703, "end": 1933857815, "inSample1": 1, "inSample2": 1}, {"start": 1933857866, "end": 1933857919, "inSample1": 1, "inSample2": 1}, {"start": 1198728729, "end": 1307800250, "inSample1": 1, "inSample2": 1}, {"start": 1933011332, "end": 1933170126, "inSample1": 1, "inSample2": 0}, {"start": 1933857948, "end": 1933857959, "inSample1": 1, "inSample2": 1}, {"start": 1307800798, "end": 1934476647, "inSample1": 1, "inSample2": 1}, {"start": 1307800525, "end": 1307800903, "inSample1": 1, "inSample2": 1}, {"start": 1307800256, "end": 1307800902, "inSample1": 0, "inSample2": 1}, {"start": 1198711166, "end": 1307800000, "inSample1": 0, "inSample2": 0}, {"start": 380541238, "end": 1198711166, "inSample1": 0, "inSample2": 1}, {"start": 289697322, "end": 1198789228, "inSample1": 0, "inSample2": 0}, {"start": 1307800737, "end": 1819504377, "inSample1": 1, "inSample2": 1}, {"start": 1307800753, "end": 1307800830, "inSample1": 1, "inSample2": 1}, {"start": 1307799433, "end": 1307799709, "inSample1": 1, "inSample2": 0}, {"start": 1933857842, "end": 1933857899, "inSample1": 1, "inSample2": 1}, {"start": 516376508, "end": 1933169976, "inSample1": 1, "inSample2": 1}, {"start": 1307799467, "end": 1307799860, "inSample1": 0, "inSample2": 0}, {"start": 1307800798, "end": 1821055790, "inSample1": 1, "inSample2": 1}, {"start": 1933857950, "end": 1933857952, "inSample1": 1, "inSample2": 0}, {"start": 1307800904, "end": 1933857749, "inSample1": 1, "inSample2": 1}, {"start": 1198711162, "end": 1933857825, "inSample1": 1, "inSample2": 1}, {"start": 1933857670, "end": 1933857672, "inSample1": 0, "inSample2": 0}, {"start": 673480325, "end": 1933857937, "inSample1": 1, "inSample2": 1}, {"start": 1934918110, "end": 1935376406, "inSample1": 1, "inSample2": 1}, {"start": 1307799868, "end": 1307800506, "inSample1": 0, "inSample2": 0}, {"start": 364378028, "end": 1198789228, "inSample1": 1, "inSample2": 1}, {"start": 1933857908, "end": 1933857913, "inSample1": 1, "inSample2": 0}, {"start": 1198789199, "end": 1935376328, "inSample1": 1, "inSample2": 1}, {"start": 1933857912, "end": 1933857919, "inSample1": 0, "inSample2": 0}, {"start": 1933857686, "end": 1934476661, "inSample1": 0, "inSample2": 1}, {"start": 1933857826, "end": 1933857856, "inSample1": 1, "inSample2": 1}, {"start": 1307800874, "end": 2306405274, "inSample1": 1, "inSample2": 1}, {"start": 364378102, "end": 1307800891, "inSample1": 0, "inSample2": 1}, {"start": 520105026, "end": 673480322, "inSample1": 1, "inSample2": 1}, {"start": 289697322, "end": 1307800096, "inSample1": 1, "inSample2": 1}, {"start": 1198728691, "end": 1307800809, "inSample1": 0, "inSample2": 1}, {"start": 1933857898, "end": 1934641371, "inSample1": 0, "inSample2": 0}, {"start": 1933857930, "end": 1933857952, "inSample1": 1, "inSample2": 0}, {"start": 1307799637, "end": 1307800798, "inSample1": 0, "inSample2": 1}, {"start": 1307799929, "end": 1933857701, "inSample1": 1, "inSample2": 1}, {"start": 364378102, "end": 1307799715, "inSample1": 1, "inSample2": 1}, {"start": 1307799454, "end": 1307800525, "inSample1": 0, "inSample2": 1}, {"start": 1933857889, "end": 2455770980, "inSample1": 1, "inSample2": 1}, {"start": 1933857688, "end": 1934476658, "inSample1": 1, "inSample2": 1}, {"start": 1198728686, "end": 1935376368, "inSample1": 0, "inSample2": 1}, {"start": 1307799709, "end": 1933857685, "inSample1": 1, "inSample2": 1}, {"start": 1933857787, "end": 1933857804, "inSample1": 1, "inSample2": 1}, {"start": 1307799433, "end": 1933857856, "inSample1": 1, "inSample2": 1}, {"start": 1933857856, "end": 1934641371, "inSample1": 1, "inSample2": 1}, {"start": 1933857743, "end": 1933857826, "inSample1": 1, "inSample2": 1}, {"start": 673480311, "end": 1933857748, "inSample1": 1, "inSample2": 1}, {"start": 1933857685, "end": 1934476660, "inSample1": 1, "inSample2": 1}, {"start": 1933169974, "end": 1933170037, "inSample1": 1, "inSample2": 1}, {"start": 1307800086, "end": 1307800484, "inSample1": 1, "inSample2": 1}, {"start": 1307799652, "end": 1307799868, "inSample1": 1, "inSample2": 1}, {"start": 1307799860, "end": 1307799898, "inSample1": 1, "inSample2": 0}, {"start": 1307799886, "end": 1307800256, "inSample1": 1, "inSample2": 0}, {"start": 1307799777, "end": 1821055723, "inSample1": 0, "inSample2": 0}, {"start": 1933857686, "end": 1933857688, "inSample1": 1, "inSample2": 0}, {"start": 1933857937, "end": 1933857938, "inSample1": 0, "inSample2": 0}, {"start": 1307800763, "end": 1821055626, "inSample1": 1, "inSample2": 1}, {"start": 1933857904, "end": 1933857908, "inSample1": 0, "inSample2": 0}, {"start": 1933169974, "end": 1933169986, "inSample1": 1, "inSample2": 1}, {"start": 1934476651, "end": 1934476660, "inSample1": 1, "inSample2": 1}, {"start": 520227659, "end": 1933857672, "inSample1": 1, "inSample2": 1}, {"start": 1307800548, "end": 1307800775, "inSample1": 1, "inSample2": 1}, {"start": 364378028, "end": 1935376273, "inSample1": 0, "inSample2": 0}, {"start": 1307800766, "end": 1934476651, "inSample1": 1, "inSample2": 1}, {"start": 1307800096, "end": 1933857703, "inSample1": 1, "inSample2": 1}, {"start": 1933857939, "end": 2010601053, "inSample1": 1, "inSample2": 1}, {"start": 1933857899, "end": 1933857910, "inSample1": 1, "inSample2": 1}, {"start": 1934476646, "end": 1934476647, "inSample1": 1, "inSample2": 1}, {"start": 1307800883, "end": 1933857799, "inSample1": 1, "inSample2": 1}, {"start": 1307800506, "end": 1307800801, "inSample1": 0, "inSample2": 0}, {"start": 380528315, "end": 1307800825, "inSample1": 1, "inSample2": 1}, {"start": 1307800484, "end": 1307800737, "inSample1": 1, "inSample2": 1}, {"start": 1307800883, "end": 1933857744, "inSample1": 1, "inSample2": 1}, {"start": 1821055699, "end": 1821055723, "inSample1": 0, "inSample2": 0}, {"start": 380541238, "end": 380541239, "inSample1": 0, "inSample2": 1}, {"start": 1933857863, "end": 1933857904, "inSample1": 1, "inSample2": 1}, {"start": 1933857748, "end": 1933857775, "inSample1": 1, "inSample2": 0}, {"start": 1307800321, "end": 1307800548, "inSample1": 1, "inSample2": 1}, {"start": 1307799777, "end": 1307800577, "inSample1": 1, "inSample2": 1}, {"start": 1933857898, "end": 1933857904, "inSample1": 1, "inSample2": 1}, {"start": 289697322, "end": 1933857703, "inSample1": 1, "inSample2": 0}, {"start": 1307799652, "end": 1307800086, "inSample1": 1, "inSample2": 1}, {"start": 673480311, "end": 1935376400, "inSample1": 1, "inSample2": 1}, {"start": 673480326, "end": 1933857938, "inSample1": 1, "inSample2": 1}, {"start": 1933857720, "end": 1934476663, "inSample1": 1, "inSample2": 0}, {"start": 1933857959, "end": 2010601200, "inSample1": 1, "inSample2": 1}, {"start": 520227659, "end": 1821055790, "inSample1": 1, "inSample2": 1}, {"start": 1933857943, "end": 2010601212, "inSample1": 1, "inSample2": 1}, {"start": 1934476647, "end": 1934476658, "inSample1": 1, "inSample2": 1}, {"start": 1933857746, "end": 1933857798, "inSample1": 1, "inSample2": 1}, {"start": 1307799433, "end": 1933857794, "inSample1": 1, "inSample2": 1}, {"start": 1934918096, "end": 1934918110, "inSample1": 1, "inSample2": 1}, {"start": 1933857932, "end": 1933857941, "inSample1": 1, "inSample2": 0}, {"start": 1933857898, "end": 1933857941, "inSample1": 1, "inSample2": 1}, {"start": 1307800145, "end": 1307800841, "inSample1": 1, "inSample2": 1}, {"start": 1307799595, "end": 1935376341, "inSample1": 1, "inSample2": 1}, {"start": 1307799495, "end": 1307800506, "inSample1": 0, "inSample2": 1}, {"start": 1307799709, "end": 1307799828, "inSample1": 1, "inSample2": 1}, {"start": 673480322, "end": 1933857960, "inSample1": 1, "inSample2": 0}, {"start": 364378028, "end": 1307800504, "inSample1": 0, "inSample2": 1}, {"start": 1307800204, "end": 1307800801, "inSample1": 1, "inSample2": 1}, {"start": 1307799448, "end": 1821055699, "inSample1": 0, "inSample2": 0}, {"start": 1307800484, "end": 1934476621, "inSample1": 1, "inSample2": 1}, {"start": 380541239, "end": 1307799655, "inSample1": 1, "inSample2": 1}, {"start": 1307800506, "end": 1307800754, "inSample1": 1, "inSample2": 1}, {"start": 1307799467, "end": 1307800874, "inSample1": 0, "inSample2": 0}, {"start": 520105026, "end": 1933857960, "inSample1": 1, "inSample2": 1}, {"start": 1307800028, "end": 1307800472, "inSample1": 1, "inSample2": 1}, {"start": 1307799467, "end": 1307800275, "inSample1": 1, "inSample2": 1}, {"start": 1307800365, "end": 1307800566, "inSample1": 1, "inSample2": 1}, {"start": 1933857743, "end": 1933857856, "inSample1": 0, "inSample2": 1}, {"start": 1933169976, "end": 1933857919, "inSample1": 1, "inSample2": 1}, {"start": 1307799655, "end": 1307800219, "inSample1": 1, "inSample2": 1}, {"start": 559386994, "end": 559387050, "inSample1": 1, "inSample2": 1}, {"start": 1307799467, "end": 1307799898, "inSample1": 0, "inSample2": 0}, {"start": 1307799454, "end": 1307799982, "inSample1": 1, "inSample2": 1}, {"start": 673480326, "end": 1933857937, "inSample1": 1, "inSample2": 1}, {"start": 673480327, "end": 1933857952, "inSample1": 1, "inSample2": 1}, {"start": 289698121, "end": 1198789196, "inSample1": 1, "inSample2": 1}, {"start": 289698121, "end": 1307800130, "inSample1": 0, "inSample2": 1}, {"start": 559387050, "end": 1307800307, "inSample1": 1, "inSample2": 1}, {"start": 1307799622, "end": 1307800548, "inSample1": 1, "inSample2": 1}, {"start": 380541239, "end": 1198728686, "inSample1": 0, "inSample2": 1}, {"start": 1307799454, "end": 1307800146, "inSample1": 1, "inSample2": 1}, {"start": 1934918096, "end": 1934918105, "inSample1": 0, "inSample2": 1}, {"start": 364378028, "end": 1933857670, "inSample1": 1, "inSample2": 1}, {"start": 1307799828, "end": 1934476661, "inSample1": 1, "inSample2": 1}, {"start": 380528314, "end": 1307800130, "inSample1": 1, "inSample2": 1}, {"start": 560002145, "end": 1933857704, "inSample1": 0, "inSample2": 0}, {"start": 1933170039, "end": 1933170126, "inSample1": 1, "inSample2": 1}, {"start": 1933857910, "end": 1933857948, "inSample1": 1, "inSample2": 1}, {"start": 1307800146, "end": 1307800367, "inSample1": 1, "inSample2": 1}, {"start": 1933857705, "end": 1933857745, "inSample1": 1, "inSample2": 0}, {"start": 1307799467, "end": 1307799763, "inSample1": 1, "inSample2": 1}, {"start": 1933857899, "end": 1933857943, "inSample1": 0, "inSample2": 0}, {"start": 1198789224, "end": 1198789226, "inSample1": 1, "inSample2": 1}, {"start": 1307800256, "end": 1307800830, "inSample1": 1, "inSample2": 1}, {"start": 1307799451, "end": 1307799566, "inSample1": 1, "inSample2": 1}, {"start": 1307799860, "end": 1307800428, "inSample1": 0, "inSample2": 0}, {"start": 1307799886, "end": 1307800753, "inSample1": 0, "inSample2": 0}, {"start": 1307800830, "end": 1307800880, "inSample1": 0, "inSample2": 0}, {"start": 520227659, "end": 1307799777, "inSample1": 1, "inSample2": 1}, {"start": 1934476638, "end": 1934476645, "inSample1": 0, "inSample2": 0}, {"start": 364378102, "end": 1307800332, "inSample1": 1, "inSample2": 0}, {"start": 1933857692, "end": 1934918084, "inSample1": 1, "inSample2": 1}, {"start": 1933857688, "end": 1934918096, "inSample1": 1, "inSample2": 1}, {"start": 1198789228, "end": 1933857678, "inSample1": 1, "inSample2": 1}, {"start": 1307799715, "end": 1935376204, "inSample1": 1, "inSample2": 1}, {"start": 1198789199, "end": 1198789224, "inSample1": 1, "inSample2": 1}, {"start": 560002145, "end": 1935376444, "inSample1": 1, "inSample2": 1}, {"start": 1307800393, "end": 1307800775, "inSample1": 1, "inSample2": 1}, {"start": 1307800127, "end": 1307800905, "inSample1": 1, "inSample2": 1}, {"start": 673480311, "end": 1198728729, "inSample1": 1, "inSample2": 1}, {"start": 1307799599, "end": 1307799886, "inSample1": 1, "inSample2": 1}, {"start": 370090296, "end": 516376508, "inSample1": 1, "inSample2": 0}, {"start": 1933857744, "end": 1933857794, "inSample1": 1, "inSample2": 1}, {"start": 1307800512, "end": 1307800775, "inSample1": 1, "inSample2": 1}, {"start": 1933857672, "end": 1933857675, "inSample1": 0, "inSample2": 1}, {"start": 1307799433, "end": 1933857743, "inSample1": 0, "inSample2": 1}, {"start": 2010601053, "end": 2455770980, "inSample1": 1, "inSample2": 1}, {"start": 1933857705, "end": 1934918084, "inSample1": 1, "inSample2": 1}, {"start": 1307799451, "end": 1307800279, "inSample1": 0, "inSample2": 0}, {"start": 1933857912, "end": 1935376454, "inSample1": 1, "inSample2": 1}, {"start": 1307800275, "end": 1307800566, "inSample1": 1, "inSample2": 1}, {"start": 1307799953, "end": 1307800307, "inSample1": 1, "inSample2": 1}, {"start": 1307800130, "end": 1307800825, "inSample1": 0, "inSample2": 0}, {"start": 1307800821, "end": 1307800891, "inSample1": 1, "inSample2": 1}, {"start": 1307799763, "end": 1307799898, "inSample1": 1, "inSample2": 1}, {"start": 1307800763, "end": 1307800845, "inSample1": 1, "inSample2": 1}, {"start": 1307799495, "end": 1307800754, "inSample1": 0, "inSample2": 1}, {"start": 1307799637, "end": 1307800007, "inSample1": 1, "inSample2": 1}, {"start": 1307799448, "end": 1307800057, "inSample1": 1, "inSample2": 1}, {"start": 1307800034, "end": 1307800057, "inSample1": 0, "inSample2": 0}, {"start": 1307800204, "end": 1307800754, "inSample1": 1, "inSample2": 1}, {"start": 1307800904, "end": 1934918105, "inSample1": 1, "inSample2": 1}, {"start": 1934476655, "end": 1934476656, "inSample1": 1, "inSample2": 1}, {"start": 1307799777, "end": 1307800202, "inSample1": 1, "inSample2": 1}, {"start": 1933857705, "end": 1934918110, "inSample1": 0, "inSample2": 1}, {"start": 560002145, "end": 1933857775, "inSample1": 1, "inSample2": 0}, {"start": 289698121, "end": 1307800821, "inSample1": 1, "inSample2": 1}, {"start": 1198711162, "end": 1307800000, "inSample1": 0, "inSample2": 1}, {"start": 1307800086, "end": 1307800702, "inSample1": 1, "inSample2": 1}, {"start": 1933857798, "end": 1933857913, "inSample1": 1, "inSample2": 1}, {"start": 1307800321, "end": 1307800873, "inSample1": 1, "inSample2": 0}, {"start": 1307799828, "end": 1307800904, "inSample1": 1, "inSample2": 1}, {"start": 1933857787, "end": 1933857815, "inSample1": 1, "inSample2": 1}, {"start": 1933857835, "end": 1933857842, "inSample1": 1, "inSample2": 1}, {"start": 380528314, "end": 1307800145, "inSample1": 1, "inSample2": 1}, {"start": 1933857720, "end": 1933857743, "inSample1": 1, "inSample2": 1}, {"start": 1934476646, "end": 1934476656, "inSample1": 1, "inSample2": 1}, {"start": 1307800214, "end": 1307800256, "inSample1": 1, "inSample2": 1}, {"start": 1307800766, "end": 1934476638, "inSample1": 1, "inSample2": 1}, {"start": 1933857913, "end": 1933857922, "inSample1": 1, "inSample2": 0}, {"start": 1307799599, "end": 1307800902, "inSample1": 1, "inSample2": 1}, {"start": 1198789196, "end": 1307800028, "inSample1": 1, "inSample2": 1}, {"start": 560002145, "end": 1198728729, "inSample1": 1, "inSample2": 1}, {"start": 1933857699, "end": 1933857701, "inSample1": 0, "inSample2": 0}, {"start": 1307799715, "end": 1307800717, "inSample1": 1, "inSample2": 1}, {"start": 1198789187, "end": 1307800761, "inSample1": 1, "inSample2": 1}, {"start": 1933857908, "end": 1933857932, "inSample1": 1, "inSample2": 1}, {"start": 559386994, "end": 1307800365, "inSample1": 1, "inSample2": 1}, {"start": 1933169986, "end": 1933170031, "inSample1": 1, "inSample2": 1}, {"start": 1198789223, "end": 1198789228, "inSample1": 1, "inSample2": 1}, {"start": 380541238, "end": 1935376368, "inSample1": 1, "inSample2": 1}, {"start": 1933857943, "end": 2010601053, "inSample1": 1, "inSample2": 1}, {"start": 1307800367, "end": 1819504178, "inSample1": 1, "inSample2": 1}, {"start": 1307799691, "end": 1307800761, "inSample1": 1, "inSample2": 1}, {"start": 1307799763, "end": 1307800393, "inSample1": 0, "inSample2": 1}, {"start": 1307800321, "end": 1307800512, "inSample1": 0, "inSample2": 1}, {"start": 1307800365, "end": 1307800874, "inSample1": 1, "inSample2": 0}, {"start": 1307799691, "end": 1935376204, "inSample1": 1, "inSample2": 1}, {"start": 1307799495, "end": 1307800057, "inSample1": 0, "inSample2": 1}, {"start": 380541238, "end": 673480311, "inSample1": 1, "inSample2": 1}, {"start": 1307799860, "end": 1307800902, "inSample1": 1, "inSample2": 0}, {"start": 380528315, "end": 1935376273, "inSample1": 0, "inSample2": 0}, {"start": 1307799467, "end": 1307800365, "inSample1": 1, "inSample2": 1}, {"start": 1198711166, "end": 1933857842, "inSample1": 1, "inSample2": 1}, {"start": 1933857748, "end": 1933857910, "inSample1": 1, "inSample2": 1}, {"start": 1933857866, "end": 1933857922, "inSample1": 1, "inSample2": 1}, {"start": 1933857910, "end": 2010601029, "inSample1": 1, "inSample2": 1}, {"start": 1821055723, "end": 1821055790, "inSample1": 1, "inSample2": 1}, {"start": 1933857964, "end": 2633386343, "inSample1": 1, "inSample2": 1}, {"start": 1198789228, "end": 1307800096, "inSample1": 1, "inSample2": 1}, {"start": 1198789187, "end": 1307800365, "inSample1": 1, "inSample2": 1}, {"start": 1307800127, "end": 1307800845, "inSample1": 1, "inSample2": 1}, {"start": 1307800798, "end": 1934476646, "inSample1": 1, "inSample2": 1}, {"start": 1933857701, "end": 1933857790, "inSample1": 1, "inSample2": 1}, {"start": 1933857787, "end": 1933857866, "inSample1": 1, "inSample2": 1}, {"start": 1198728729, "end": 1933857704, "inSample1": 1, "inSample2": 1}, {"start": 1933857775, "end": 1933857921, "inSample1": 0, "inSample2": 1}, {"start": 673480325, "end": 673480327, "inSample1": 1, "inSample2": 1}, {"start": 1307799597, "end": 1307800798, "inSample1": 1, "inSample2": 1}, {"start": 1933857701, "end": 1933857758, "inSample1": 1, "inSample2": 0}, {"start": 1307799599, "end": 1307799860, "inSample1": 1, "inSample2": 1}, {"start": 1307799709, "end": 1933857720, "inSample1": 1, "inSample2": 1}, {"start": 289697322, "end": 1933857692, "inSample1": 1, "inSample2": 1}, {"start": 1307800000, "end": 1935376368, "inSample1": 0, "inSample2": 1}, {"start": 1933857889, "end": 1933857939, "inSample1": 0, "inSample2": 1}, {"start": 1933857921, "end": 1933857950, "inSample1": 1, "inSample2": 1}, {"start": 1307800214, "end": 1307800715, "inSample1": 1, "inSample2": 1}, {"start": 420298907, "end": 1933857826, "inSample1": 1, "inSample2": 1}, {"start": 1307800219, "end": 1307800809, "inSample1": 1, "inSample2": 1}, {"start": 1307799763, "end": 1307800548, "inSample1": 0, "inSample2": 0}, {"start": 1933857799, "end": 1933857908, "inSample1": 1, "inSample2": 1}, {"start": 1933169993, "end": 1933170039, "inSample1": 1, "inSample2": 1}, {"start": 1307799597, "end": 1307800034, "inSample1": 1, "inSample2": 1}, {"start": 1307800717, "end": 1307800809, "inSample1": 1, "inSample2": 1}, {"start": 1307800141, "end": 1307800367, "inSample1": 1, "inSample2": 1}, {"start": 1307800096, "end": 1933857701, "inSample1": 1, "inSample2": 1}, {"start": 1198711162, "end": 1307799595, "inSample1": 1, "inSample2": 1}, {"start": 1933857930, "end": 1935376451, "inSample1": 1, "inSample2": 1}, {"start": 1307799454, "end": 1307800610, "inSample1": 1, "inSample2": 1}, {"start": 1933857937, "end": 1935376450, "inSample1": 1, "inSample2": 1}, {"start": 673480322, "end": 1933169976, "inSample1": 0, "inSample2": 1}, {"start": 1307800214, "end": 1307800873, "inSample1": 0, "inSample2": 1}, {"start": 1307800081, "end": 1935376368, "inSample1": 1, "inSample2": 1}, {"start": 1933169974, "end": 1933169976, "inSample1": 1, "inSample2": 1}, {"start": 1934476652, "end": 1934476655, "inSample1": 1, "inSample2": 0}, {"start": 1934476633, "end": 1934476645, "inSample1": 1, "inSample2": 1}, {"start": 1933857921, "end": 1933857930, "inSample1": 0, "inSample2": 1}, {"start": 1307800825, "end": 1307800891, "inSample1": 1, "inSample2": 1}, {"start": 1933857798, "end": 1933857799, "inSample1": 1, "inSample2": 1}, {"start": 1933857758, "end": 1933857815, "inSample1": 1, "inSample2": 1}, {"start": 1307800868, "end": 1935376341, "inSample1": 1, "inSample2": 1}, {"start": 1307800472, "end": 1307800821, "inSample1": 1, "inSample2": 1}, {"start": 1307800904, "end": 1934918110, "inSample1": 0, "inSample2": 1}, {"start": 1307800113, "end": 1307800823, "inSample1": 1, "inSample2": 1}, {"start": 1933857856, "end": 1933857898, "inSample1": 1, "inSample2": 1}, {"start": 1307800275, "end": 1307800428, "inSample1": 1, "inSample2": 1}, {"start": 1934476645, "end": 1934476655, "inSample1": 1, "inSample2": 1}, {"start": 520227659, "end": 1933857670, "inSample1": 1, "inSample2": 1}, {"start": 1933011313, "end": 1933011332, "inSample1": 1, "inSample2": 1}, {"start": 1307799451, "end": 1307800841, "inSample1": 1, "inSample2": 0}, {"start": 1307799566, "end": 1307800512, "inSample1": 1, "inSample2": 1}, {"start": 1934476656, "end": 1934476658, "inSample1": 0, "inSample2": 0}, {"start": 2010601148, "end": 2010601212, "inSample1": 1, "inSample2": 1}, {"start": 1198789226, "end": 1935376328, "inSample1": 0, "inSample2": 1}, {"start": 1307800753, "end": 1307800905, "inSample1": 1, "inSample2": 1}, {"start": 1307799886, "end": 3090332718, "inSample1": 1, "inSample2": 1}, {"start": 1933857672, "end": 1934476647, "inSample1": 0, "inSample2": 0}, {"start": 289698121, "end": 1307800393, "inSample1": 1, "inSample2": 0}, {"start": 420298907, "end": 1933857743, "inSample1": 1, "inSample2": 0}, {"start": 1307799637, "end": 1307800034, "inSample1": 1, "inSample2": 1}, {"start": 1307800028, "end": 1307800761, "inSample1": 1, "inSample2": 0}, {"start": 1198728686, "end": 1198728691, "inSample1": 1, "inSample2": 1}, {"start": 1307800702, "end": 1819504312, "inSample1": 1, "inSample2": 1}, {"start": 1933857746, "end": 1933857749, "inSample1": 0, "inSample2": 0}, {"start": 1307800472, "end": 1935376204, "inSample1": 0, "inSample2": 0}, {"start": 1307799811, "end": 1307800891, "inSample1": 0, "inSample2": 1}, {"start": 1307799448, "end": 1307800525, "inSample1": 0, "inSample2": 1}, {"start": 1933857685, "end": 1934476652, "inSample1": 1, "inSample2": 1}, {"start": 1933857688, "end": 1933857692, "inSample1": 0, "inSample2": 0}, {"start": 1307800577, "end": 1307800907, "inSample1": 1, "inSample2": 1}]